Workbook

Sheet Comparativo
A1: Nome | B1: Valor Setup (R$) | C1: Valor Mensal (R$) | D1: Outros Valores (R$) | E1: Observação / Benefícios (1 linha sem quebra)
A2: Klaviyo | B2: =Premissas_e_Fontes!B4*Premissas_e_Fontes!$B$1 -> 0 | C2: =Premissas_e_Fontes!C4*Premissas_e_Fontes!$B$1 -> 103.2 | D2: SMS +R$77,40 base no plano Email+SMS; excedente ~R$0,05-0,16/SMS e MMS 3x + taxa de operadora por país; WhatsApp ~R$0,13/conversa Meta; excedente de perfis sobe de faixa automaticamente. | E2: B2C CRM omnichannel com integração nativa Shopify 1-clique (pedidos, carrinho, catálogo em tempo real): email + SMS + WhatsApp + push no mesmo perfil com flows prontos (abandono 3 emails 48-72h recupera 5-11% e 3-8% da receita, welcome, pós-compra, winback, back-in-stock), segmentação/CDP, testes A/B, atribuição de receita, IA Composer/Customer Agent e 350+ integrações; melhor custo-benefício para moda a partir de lista pequena, escala por perfis e paga-se com 1-2 carrinhos (ticket R$550-619); atenção ao database bloat (cobra todos perfis ativos) e SMS BR mais caro que EUA.
A3: Omnisend | B3: =Premissas_e_Fontes!B5*Premissas_e_Fontes!$B$1 -> 0 | C3: =Premissas_e_Fontes!C5*Premissas_e_Fontes!$B$1 -> 82.56 | D3: Pro + SMS add-on a partir de R$0,04/SMS (EUA, varia por país/volume: R$0,05 até R$257,99 / R$0,04 até R$5.159 / R$0,04 até R$51.599); Standard sem SMS (só Pro); desconto de 30% nos 3 primeiros meses no pré-pago trimestral. | E3: Email+SMS+push com integração nativa Shopify e nota 4,8/5: editor drag-drop com 250+ templates, popups/forms com IA, automações pré-montadas (abandono, welcome, pós-compra), IA de texto/recomendação de produto e conteúdo dinâmico no Pro, push ilimitado, relatórios avançados e suporte 24/7 até no Free; Standard ideal p/ começar só email e Pro quando precisar de SMS/ilimitado; mais barato que Klaviyo na entrada e ótimo p/ Scalon validar remarketing antes de escalar.
A4: Brevo | B4: =Premissas_e_Fontes!B6*Premissas_e_Fontes!$B$1 -> 0 | C4: =Premissas_e_Fontes!C6*Premissas_e_Fontes!$B$1 -> 46.44 | D4: SMS/WhatsApp por créditos avulsos a partir de 100 créditos (nunca expiram; preço por país + tamanho da msg + tipo de template WhatsApp); add-ons: remover logo ~R$46,44/mês, IP dedicado ~R$1.295,16/ano, SSO ~R$1.671,84/mês; créditos email avulsos sem expirar. | E4: Multicanal (email, SMS, WhatsApp, chat, push, transacional com API/SMTP) com integração nativa Shopify: automações, formulários, CRM de vendas e créditos pré-pagos que nunca expiram (bom p/ envio irregular); Standard libera heatmaps/relatórios e Professional libera WhatsApp+multiusuário; ponto forte é custo por envio baixo e tudo num lugar, ponto fraco é ecommerce menos profundo que Klaviyo/Omnisend e SMS BR por crédito paulatino — ideal se Scalon quer custo baixo e WhatsApp futuro no mesmo painel.
A5: Mailchimp | B5: =Premissas_e_Fontes!B7*Premissas_e_Fontes!$B$1 -> 0 | C5: =Premissas_e_Fontes!C7*Premissas_e_Fontes!$B$1 -> 67.08 | D5: SMS add-on cobrado à parte por país/operadora; excedente de contatos muda de faixa (ex.: ~R$232,20 em 2.500 e ~R$516,00 em 5k no Standard); Premium multinível para 200k+; anual com desconto via vendas. | E5: Email com integração nativa Shopify (pedidos/produtos/cupons): templates, jornadas básicas no Essentials (4 passos) e multietapas + IA + segmentação preditiva no Standard, testes multivariados e assentos ilimitados no Premium; entrega e suporte bons mas automação ecommerce e custo por contato ficam piores que Klaviyo/Omnisend ao escalar e SMS é fraco fora EUA; serve p/ Scalon se time já conhece, mas não é o melhor custo-benefício p/ remarketing avançado.
A6: ActiveCampaign | B6: =Premissas_e_Fontes!B8*Premissas_e_Fontes!$B$1 -> 0 | C6: =Premissas_e_Fontes!C8*Premissas_e_Fontes!$B$1 -> 149.64 | D6: SMS/WhatsApp por créditos/uso além da assinatura (varia por país); usuários e objetos customizados sobem o plano; sem taxa de setup; trial + migração/onboarding inclusos no início. | E6: Automação + CRM com integrações nativas Shopify/Woo (standard e premium por tier): email + WhatsApp + SMS add-on, landing pages, conteúdo preditivo/condicional, atribuição, objetos customizados, +1.000 integrações e IA Active Intelligence; forte em nutrição/B2B e réguas complexas, ecommerce bom mas menos pronto que Klaviyo (exige mais construção); bom se Scalon quiser CRM comercial junto, senão paga complexidade desnecessária.
A7: Drip | B7: =Premissas_e_Fontes!B9*Premissas_e_Fontes!$B$1 -> 0 | C7: =Premissas_e_Fontes!C9*Premissas_e_Fontes!$B$1 -> 201.24 | D7: Excedente por contatos acima de 2.500 (faixas automáticas); SMS via integração (Twilio/Postscript) cobrado à parte; sem taxa de setup. | E7: CRM ecommerce com integração nativa Shopify profunda (comportamento, LTV, RFM): email ilimitado por contato, workflows visuais, popups/forms, segmentação preditiva e playbooks de abandono/winback específicos p/ loja; simples de operar e ótimo p/ D2C, porém sem SMS/WhatsApp nativo forte (usa integração) e sem plano free — faz sentido se Scalon quer só email ecommerce poderoso e já resolve SMS/WhatsApp em outro app.
A8: GetResponse | B8: =Premissas_e_Fontes!B10*Premissas_e_Fontes!$B$1 -> 0 | C8: =Premissas_e_Fontes!C10*Premissas_e_Fontes!$B$1 -> 98.04 | D8: Excedente por lista (2,5k/5k/10k/25k/50k/100k); SMS, push e recomendações IA no Enterprise; 18% off no anual; trial de 14 dias. | E8: Email + automação + ecommerce com integração nativa Shopify: newsletters ilimitadas, editor visual, DKIM custom, timing perfeito, A/B, tracking ecommerce/GA, landing pages ilimitadas no Marketer, cursos/newsletters pagas/webinars no Creator e push/SMS/recomendação IA no Enterprise; barato na entrada e bom p/ conteúdo + loja, mas remarketing menos especializado que Klaviyo/Omnisend e WhatsApp só no Enterprise — alternativa econômica se Scalon prioriza custo e cursos/conteúdo.
A9: Yotpo Reviews | B9: =Premissas_e_Fontes!B11*Premissas_e_Fontes!$B$1 -> 0 | C9: =Premissas_e_Fontes!C11*Premissas_e_Fontes!$B$1 -> 77.4 | D9: Cobrança por volume de pedidos/mês + overage; Pro/Premium exigem anual em geral e sem downgrade no ciclo; bundle Reviews+Loyalty economiza até 35%; implementação Enterprise à parte. | E9: Reviews/UGC + Loyalty com integração nativa Shopify e com Klaviyo/Omnisend/Attentive: coleta automática pós-compra com fotos/vídeos, widgets, carrossel, rich snippets Google, moderação, SEO e analytics que alimentam as estrelas do protótipo (4,9/212) e aumentam conversão; ATENÇÃO Email/SMS próprios foram descontinuados em 31/12/2025 (usar Klaviyo/Omnisend p/ disparo); cobrança por pedidos/mês com anual e sem downgrade — essencial p/ prova social da Scalon, não como disparador.
A10: Postscript SMS | B10: =Premissas_e_Fontes!B12*Premissas_e_Fontes!$B$1 -> 0 | C10: =Premissas_e_Fontes!C12*Premissas_e_Fontes!$B$1 -> 252.84 | D10: Tudo além do mínimo é por mensagem: SMS R$0,05/0,04/0,04 por plano + MMS R$0,23/0,15/0,12 + operadora média R$0,02/SMS e R$0,04/MMS (EUA/Canadá; demais países por tabela); acima de 160 caracteres (70 com emoji) conta múltiplos. | E10: SMS especializado Shopify com integração nativa 1-clique (checkout, carrinho, pós-compra, quiz, loyalty): campanhas/automações, segmentos ilimitados, número toll-free, keywords, links curtos branded no Pro, CSM/onboarding nos tiers altos e conformidade TCPA; SMS converte 8-12% clique e soma 1-3pp sobre email no abandono (ideal como 2º toque em 1-2h após email não aberto); EUA-ótimo, BR checar cobertura/preço por país + carrier — usar sobre o email (Klaviyo/Omnisend), não sozinho.
A11: Attentive | B11: =Premissas_e_Fontes!B13*Premissas_e_Fontes!$B$1 -> 0 | C11: =Premissas_e_Fontes!C13*Premissas_e_Fontes!$B$1 -> 2580 | D11: Proposta custom: plataforma + por mensagem + operadora + onboarding/gerenciado; anual recorrente; overage e serviços (CSM, criativo, migração) à parte — pedir escopo fechado em R$. Entrada típica estimada R$1.548,00-5.160,00/mês. | E11: SMS/email gerenciado enterprise com integração nativa Shopify (concierge, deliverability, criativo, compliance por estado): automações, segmentação granular, journeys via API e mensageria RCS/WhatsApp conforme proposta; entrega e serviço premium p/ grandes volumes, porém sem preço público, com anual e dependência do time do fornecedor; só faz sentido p/ Scalon após escalar muito (+R$300k/mês) — hoje é overkill.
A12: Privy | B12: =Premissas_e_Fontes!B14*Premissas_e_Fontes!$B$1 -> 0 | C12: =Premissas_e_Fontes!C14*Premissas_e_Fontes!$B$1 -> 154.8 | D12: Email por nº máximo de contatos contatáveis no ciclo (ex.: 1,5-2k R$232,20; 2-3k R$309,60; 9-10k R$851,40; 24-25k R$2.012,40) + SMS por pacotes além dos 250 inclusos (ex.: R$77,40/1.250 créditos); Displays por pageviews (25k R$247,68; 50k R$433,44; 100k R$866,88). | E12: Popups + email + SMS com integração nativa Shopify e foco em facilidade: popups/displays com targeting avançado/quiz, email ilimitado com templates/flows/segmentação e SMS marketing no plano combinado, relatórios de receita e estrategistas opcionais; entrada barata e rápida p/ capturar (Quero 10% OFF) e salvar carrinho sem especialista, mas automação/IA e ecommerce menos profundos que Klaviyo/Omnisend e sem free novo — bom p/ Scalon começar captura+email simples.
A13: Justuno | B13: =Premissas_e_Fontes!B15*Premissas_e_Fontes!$B$1 -> 0 | C13: =Premissas_e_Fontes!C15*Premissas_e_Fontes!$B$1 -> 304.44 | D13: Excedente por visitors acima de 10k no Lite / 20k no Done-for-you; verificação instantânea email/SMS, Spotlight e assentos extras conforme plano; sem contrato, trial de 14-30 dias. | E13: Captura/CRO com integração nativa Shopify (JS + app): popups inteligentes por comportamento, identificação de visitante, verificação instantânea, testes e estrategista CRO (no Done-for-you com Slack e gerente dedicados); não é disparador de email/SMS (empurra p/ Klaviyo/Brevo), mas aumenta base e intenção antes do abandono; ideal como camada de topo do funil da Scalon sobre o CRM.
... A21: Sendlane | B21: =Premissas_e_Fontes!B23*Premissas_e_Fontes!$B$1 -> 0 | C21: =Premissas_e_Fontes!C23*Premissas_e_Fontes!$B$1 -> 510.84 | D21: Excedente por contatos + SMS por uso + onboarding; revisões de deliverability e migração inclusas nos tiers altos; trial disponível. Entrada ~R$510,84/2.500 contatos. | E21: Email+SMS+reviews com integração nativa Shopify profunda (eventos, catálogo, cupons): automação unificada, segmentação, deliverability gerenciada e playbooks D2C com trial e migração assistida; operação simples e tudo num lugar p/ loja, porém entrada mais cara (R$99) e sem WhatsApp BR forte/precificação pública detalhada BR — avaliar se ticket/lista da Scalon já justificam.
A22: TOTAL DE OPÇÕES | B22: =COUNTA(A2:A21) -> 20

Sheet Premissas_e_Fontes
A1: Câmbio USD->BRL = 5,16 (dólar venda 14/09/2026, ~R$5,161 InfoMoney/Folha; ref Investing/XE ~R$5,11) | B1: 5.16
A2: Data da conversão: 14/09/2026. Aba Comparativo 100% em R$: Setup e Mensal via fórmula =USD*Câmbio; Outros Valores e Observações convertidos para R$ (sem US$). Verificar preço final no site oficial antes de contratar.
A3: Ferramenta | B3: Setup USD | C3: Mensal USD base | D3: Fonte oficial (preço base)
A4: Klaviyo | B4: 0 | C4: 20 | D4: klaviyo.com/pricing - Email 500 perfis; Free 250 perfis/500 envios
A5: Omnisend | B5: 0 | C5: 16 | D5: omnisend.com/pricing + apps.shopify.com/omnisend - Standard 500 contatos; Free 250/500
A6: Brevo | B6: 0 | C6: 9 | D6: brevo.com/pricing + help.brevo.com - Starter 5k emails/mês
A7: Mailchimp | B7: 0 | C7: 13 | D7: mailchimp.com/pricing - Essentials 500 contatos; Free 250/500
A8: ActiveCampaign | B8: 0 | C8: 29 | D8: activecampaign.com/pricing - Starter ~1k contatos; sem setup
A9: Drip | B9: 0 | C9: 39 | D9: drip.com/pricing - até 2.500 contatos, trial 14d
A10: GetResponse | B10: 0 | C10: 19 | D10: getresponse.com/pricing - Starter 1k contatos ilimitado, -18% anual
A11: Yotpo Reviews | B11: 0 | C11: 15 | D11: yotpo.com/pricing - Starter até 50 pedidos/mês; Email/SMS descontinuados em 31/12/2025
A12: Postscript SMS | B12: 0 | C12: 49 | D12: postscript.io/pricing - Starter $0 + mínimo $49; $0.009/SMS + carrier
A13: Attentive | B13: 0 | C13: 500 | D13: attentive.com - quote custom/anual; entrada típica $300-1000+ (estimativa)
A14: Privy | B14: 0 | C14: 30 | D14: privy.com/pricing + apps.shopify.com/privy - Email 1.500 contatos; Displays $24/10k views
A15: Justuno | B15: 0 | C15: 59 | D15: justuno.com/pricing - Lite 10k visitors; Done-for-you $299/20k
... A23: Sendlane | B23: 0 | C23: 99 | D23: sendlane.com - Starter 2.500 contatos
